henzcli/__init__.py
henzcli/__main__.py
henzcli/main.py
henzcli-0.1.3.dist-info/LICENSE
henzcli-0.1.3.dist-info/METADATA
henzcli-0.1.3.dist-info/WHEEL
henzcli-0.1.3.dist-info/entry_points.txt
henzcli-0.1.3.dist-info/top_level.txt
henzcli-0.1.3.dist-info/RECORD
