Metadata-Version: 2.1
Name: henzcli
Version: 0.1.3
Summary: CLI tool to check healthy links
Home-page: https://github.com/HenryZerocool/henzcli
Author: Henry Zerocool
Author-email: phnguyen7@myseneca.ca
License: MIT
Platform: UNKNOWN
Classifier: Programming Language :: Python :: 3
Classifier: License :: OSI Approved :: MIT License
Classifier: Operating System :: OS Independent
Requires-Python: >=3.6
Requires-Dist: requests (==2.24.0)
Requires-Dist: beautifulsoup4 (==4.9.1)
Requires-Dist: datetime (==4.3)
Requires-Dist: colorama (==0.4.4)
Requires-Dist: black (==20.8b1)
Requires-Dist: flake8 (==3.8.4)
Requires-Dist: pytest (==6.1.2)
Requires-Dist: pytest-cov (==2.10.1)
Requires-Dist: python-dotenv
